pgnotify/__init__.py
pgnotify/notify.py
pgnotify-0.1.1561372201.dist-info/LICENSE
pgnotify-0.1.1561372201.dist-info/WHEEL
pgnotify-0.1.1561372201.dist-info/METADATA
pgnotify-0.1.1561372201.dist-info/RECORD
