Metadata-Version: 2.1
Name: pgnotify
Version: 0.1.1561372201
Summary: Easily LISTEN to PostgreSQL NOTIFY notifications
Home-page: https://github.com/djrobstep/pgnotify
License: Unlicense
Author: Robert Lechte
Author-email: robertlechte@gmail.com
Classifier: License :: Other/Proprietary License
Classifier: Programming Language :: Python :: 2
Classifier: Programming Language :: Python :: 2.7
Classifier: Programming Language :: Python :: 3
Classifier: Programming Language :: Python :: 3.4
Classifier: Programming Language :: Python :: 3.5
Classifier: Programming Language :: Python :: 3.6
Classifier: Programming Language :: Python :: 3.7
Requires-Dist: logx
Requires-Dist: psycopg2-binary
Project-URL: Repository, https://github.com/djrobstep/pgnotify
